prodigy_prot/__init__.py
prodigy_prot/cli.py
prodigy_prot/data/naccess.config
prodigy_prot/modules/__init__.py
prodigy_prot/modules/aa_properties.py
prodigy_prot/modules/freesasa_tools.py
prodigy_prot/modules/models.py
prodigy_prot/modules/parsers.py
prodigy_prot/modules/prodigy.py
prodigy_prot/modules/utils.py
prodigy_prot-2.3.0.dist-info/METADATA
prodigy_prot-2.3.0.dist-info/WHEEL
prodigy_prot-2.3.0.dist-info/entry_points.txt
prodigy_prot-2.3.0.dist-info/licenses/LICENSE
prodigy_prot-2.3.0.dist-info/RECORD
