Metadata-Version: 2.4
Name: prodigy-prot
Version: 2.3.0
Summary: PROtein binDIng enerGY prediction
Author: Anna Vangone, Joao Rodrigues, Joerg Schaarschmidt
Maintainer-email: BonvinLab <bonvinlab.support@uu.nl>
License-Expression: Apache-2.0
License-File: LICENSE
Classifier: Development Status :: 5 - Production/Stable
Classifier: Programming Language :: Python :: 3.9
Classifier: Programming Language :: Python :: 3.10
Classifier: Programming Language :: Python :: 3.11
Classifier: Programming Language :: Python :: 3.12
Classifier: Programming Language :: Python :: 3.13
Classifier: Topic :: Scientific/Engineering :: Bio-Informatics
Classifier: Topic :: Scientific/Engineering :: Chemistry
Requires-Dist: biopython>=1.80
Requires-Dist: freesasa>=2.2.1
Requires-Dist: numpy>=2
Provides-Extra: dev
Requires-Dist: coverage; extra == 'dev'
Requires-Dist: hypothesis; extra == 'dev'
Requires-Dist: mypy; extra == 'dev'
Requires-Dist: pytest; extra == 'dev'
Requires-Dist: pytest-cov; extra == 'dev'
